<Properties StartupConfiguration="{16CA64E6-A0C2-4352-A631-1EB4136DE77B}|Default">
  <MonoDevelop.Ide.ItemProperties.Moyenne_220des_2202_220nombres PreferredExecutionTarget="MonoDevelop.Default" />
  <MonoDevelop.Ide.Workbench ActiveDocument="Program.cs">
    <Files>
      <File FileName="../2.5 RechercheDesDiviseursD'UnNombre/Program.cs" Line="1" Column="1" />
      <File FileName="Program.cs" Line="1" Column="1" />
    </Files>
    <Pads>
      <Pad Id="ProjectPad">
        <State name="__root__">
          <Node name="Moyenne des 2 nombres" expanded="True">
            <Node name="Moyenne des 2 nombres" expanded="True">
              <Node name="Program.cs" selected="True" />
            </Node>
          </Node>
        </State>
      </Pad>
      <Pad Id="MonoDevelop.Debugger.WatchPad">
        <State />
      </Pad>
    </Pads>
  </MonoDevelop.Ide.Workbench>
  <MonoDevelop.Ide.Workspace ActiveConfiguration="Debug" />
  <MonoDevelop.Ide.DebuggingService.Breakpoints>
    <BreakpointStore />
  </MonoDevelop.Ide.DebuggingService.Breakpoints>
  <MultiItemStartupConfigurations />
  <MonoDevelop.Ide.DebuggingService.PinnedWatches />
</Properties>